setup.py
digitalocean/__init__.py
digitalocean/exceptions.py
digitalocean/models.py
digitalocean/session.py
digitalocean/utils.py
pyocean.egg-info/PKG-INFO
pyocean.egg-info/SOURCES.txt
pyocean.egg-info/dependency_links.txt
pyocean.egg-info/top_level.txt