Metadata-Version: 1.0
Name: pyocean
Version: 0.1.3
Summary: Digital Ocean API
Home-page: https://github.com/mylokin/digitalocean
Author: Andrey Gubarev
Author-email: mylokin@me.com
License: UNKNOWN
Platform: UNKNOWN
